mezo/__init__.py
mezo/distributed.py
mezo/mezo.py
mezo-0.0.1.dist-info/LICENSE
mezo-0.0.1.dist-info/METADATA
mezo-0.0.1.dist-info/WHEEL
mezo-0.0.1.dist-info/RECORD
