Metadata-Version: 2.1
Name: mezo
Version: 0.0.1
Summary: Fine-tuning LLMs using Forward Passes
License: MIT
Author: Sadhika Malladi
Author-email: smalladi@princeton.edu
Requires-Python: >=3.11,<4.0
Classifier: License :: OSI Approved :: MIT License
Classifier: Programming Language :: Python :: 3
Classifier: Programming Language :: Python :: 3.11
Classifier: Programming Language :: Python :: 3.12
Requires-Dist: datasets (>=2.15.0,<3.0.0)
Requires-Dist: torch (>=2.1.2,<3.0.0)
Requires-Dist: tqdm (>=4.66.1,<5.0.0)
Requires-Dist: transformers (>=4.36.2,<5.0.0)
